pytest_report_parameters.py
pytest_report_parameters-0.6.0.dist-info/METADATA
pytest_report_parameters-0.6.0.dist-info/WHEEL
pytest_report_parameters-0.6.0.dist-info/entry_points.txt
pytest_report_parameters-0.6.0.dist-info/top_level.txt
pytest_report_parameters-0.6.0.dist-info/RECORD
